flask_lambda.py
flask_lambda-0.0.4.dist-info/DESCRIPTION.rst
flask_lambda-0.0.4.dist-info/METADATA
flask_lambda-0.0.4.dist-info/RECORD
flask_lambda-0.0.4.dist-info/WHEEL
flask_lambda-0.0.4.dist-info/metadata.json
flask_lambda-0.0.4.dist-info/top_level.txt
