Metadata-Version: 1.1
Name: flask-lambda
Version: 0.0.4
Summary: Python module to make Flask compatible with AWS Lambda for creating RESTful applications
Home-page: https://github.com/sivel/flask-lambda
Author: Matt Martz
Author-email: matt@sivel.net
License: Apache License, Version 2.0
Keywords: flask aws amazon lambda
Platform: UNKNOWN
Classifier: Development Status :: 4 - Beta
Classifier: Programming Language :: Python
Classifier: Environment :: Console
Classifier: Operating System :: POSIX
Classifier: Programming Language :: Python :: 2
Classifier: Programming Language :: Python :: 2.7
Classifier: Programming Language :: Python :: 3
Classifier: Programming Language :: Python :: 3.5
Classifier: Intended Audience :: Developers
Classifier: Natural Language :: English
Classifier: Topic :: Utilities
Classifier: License :: OSI Approved :: Apache Software License
